{
 "CoulombPotential": [
  {
   "is_class": false,
   "is_explicit": true,
   "module": "builtins",
   "module_short": "builtins",
   "name": "CoulombPotential"
  }
 ],
 "Optional": [
  {
   "is_class": false,
   "is_explicit": false,
   "module": "typing",
   "module_short": "typing",
   "name": "_SpecialForm"
  },
  {
   "is_class": false,
   "is_explicit": false,
   "module": "typing",
   "module_short": "typing",
   "name": "Optional"
  }
 ],
 "PMECalculator": [
  {
   "is_class": false,
   "is_explicit": true,
   "module": "builtins",
   "module_short": "builtins",
   "name": "PMECalculator"
  }
 ],
 "S": [
  {
   "is_class": false,
   "is_explicit": false,
   "module": "numpy",
   "module_short": "numpy",
   "name": "ndarray"
  }
 ],
 "True": [
  {
   "is_class": false,
   "is_explicit": true,
   "module": "builtins",
   "module_short": "builtins",
   "name": "True"
  }
 ],
 "ase.Atoms": [
  {
   "is_class": true,
   "is_explicit": false,
   "module": "ase.atoms",
   "module_short": "ase",
   "name": "Atoms"
  },
  {
   "is_class": true,
   "is_explicit": false,
   "module": "ase",
   "module_short": "ase",
   "name": "Atoms"
  },
  {
   "is_class": false,
   "is_explicit": false,
   "module": "ase",
   "module_short": "ase",
   "name": "Atoms"
  }
 ],
 "atoms": [
  {
   "is_class": false,
   "is_explicit": false,
   "module": "ase.atoms",
   "module_short": "ase",
   "name": "Atoms"
  },
  {
   "is_class": false,
   "is_explicit": false,
   "module": "ase",
   "module_short": "ase",
   "name": "Atoms"
  }
 ],
 "atoms.cell.array": [
  {
   "is_class": false,
   "is_explicit": false,
   "module": "ase.atoms",
   "module_short": "ase",
   "name": "Atoms.cell"
  },
  {
   "is_class": false,
   "is_explicit": false,
   "module": "ase",
   "module_short": "ase",
   "name": "Atoms.cell"
  }
 ],
 "atoms.positions": [
  {
   "is_class": false,
   "is_explicit": false,
   "module": "ase.atoms",
   "module_short": "ase",
   "name": "Atoms.positions"
  },
  {
   "is_class": false,
   "is_explicit": false,
   "module": "ase",
   "module_short": "ase",
   "name": "Atoms.positions"
  }
 ],
 "atoms_unitcell": [
  {
   "is_class": false,
   "is_explicit": false,
   "module": "ase.atoms",
   "module_short": "ase",
   "name": "Atoms"
  },
  {
   "is_class": false,
   "is_explicit": false,
   "module": "ase",
   "module_short": "ase",
   "name": "Atoms"
  }
 ],
 "atoms_unitcell.repeat": [
  {
   "is_class": false,
   "is_explicit": false,
   "module": "ase.atoms",
   "module_short": "ase",
   "name": "Atoms.repeat"
  },
  {
   "is_class": false,
   "is_explicit": false,
   "module": "ase",
   "module_short": "ase",
   "name": "Atoms.repeat"
  }
 ],
 "cell": [
  {
   "is_class": false,
   "is_explicit": false,
   "module": "torch",
   "module_short": "torch",
   "name": "Tensor"
  }
 ],
 "cell.dtype": [
  {
   "is_class": false,
   "is_explicit": false,
   "module": "torch",
   "module_short": "torch",
   "name": "dtype"
  }
 ],
 "charges": [
  {
   "is_class": false,
   "is_explicit": false,
   "module": "torch",
   "module_short": "torch",
   "name": "Tensor"
  }
 ],
 "charges.T": [
  {
   "is_class": false,
   "is_explicit": false,
   "module": "torch",
   "module_short": "torch",
   "name": "Tensor"
  }
 ],
 "charges_unitcell": [
  {
   "is_class": false,
   "is_explicit": false,
   "module": "numpy",
   "module_short": "numpy",
   "name": "ndarray"
  }
 ],
 "chemiscope.quick_settings": [
  {
   "is_class": false,
   "is_explicit": false,
   "module": "builtins",
   "module_short": "builtins",
   "name": "function"
  },
  {
   "is_class": false,
   "is_explicit": false,
   "module": "chemiscope",
   "module_short": "chemiscope",
   "name": "quick_settings"
  }
 ],
 "chemiscope.show": [
  {
   "is_class": false,
   "is_explicit": false,
   "module": "builtins",
   "module_short": "builtins",
   "name": "function"
  },
  {
   "is_class": false,
   "is_explicit": false,
   "module": "chemiscope",
   "module_short": "chemiscope",
   "name": "show"
  }
 ],
 "cutoff": [
  {
   "is_class": false,
   "is_explicit": false,
   "module": "builtins",
   "module_short": "builtins",
   "name": "float"
  }
 ],
 "d": [
  {
   "is_class": false,
   "is_explicit": false,
   "module": "torch",
   "module_short": "torch",
   "name": "Tensor"
  }
 ],
 "displacement": [
  {
   "is_class": false,
   "is_explicit": false,
   "module": "numpy",
   "module_short": "numpy",
   "name": "ndarray"
  }
 ],
 "distances": [
  {
   "is_class": false,
   "is_explicit": false,
   "module": "builtins",
   "module_short": "builtins",
   "name": "function"
  }
 ],
 "energy": [
  {
   "is_class": false,
   "is_explicit": false,
   "module": "torch",
   "module_short": "torch",
   "name": "Tensor"
  }
 ],
 "energy_new": [
  {
   "is_class": false,
   "is_explicit": false,
   "module": "torch",
   "module_short": "torch",
   "name": "Tensor"
  }
 ],
 "forces": [
  {
   "is_class": false,
   "is_explicit": false,
   "module": "torch",
   "module_short": "torch",
   "name": "Tensor"
  }
 ],
 "forces_new": [
  {
   "is_class": false,
   "is_explicit": false,
   "module": "torch",
   "module_short": "torch",
   "name": "Tensor"
  }
 ],
 "i": [
  {
   "is_class": false,
   "is_explicit": false,
   "module": "torch",
   "module_short": "torch",
   "name": "Tensor"
  }
 ],
 "i.astype": [
  {
   "is_class": false,
   "is_explicit": false,
   "module": "torch",
   "module_short": "torch",
   "name": "Tensor"
  }
 ],
 "j": [
  {
   "is_class": false,
   "is_explicit": false,
   "module": "torch",
   "module_short": "torch",
   "name": "Tensor"
  }
 ],
 "j.astype": [
  {
   "is_class": false,
   "is_explicit": false,
   "module": "torch",
   "module_short": "torch",
   "name": "Tensor"
  }
 ],
 "neighbor_distances": [
  {
   "is_class": false,
   "is_explicit": false,
   "module": "torch",
   "module_short": "torch",
   "name": "Tensor"
  }
 ],
 "neighbor_indices": [
  {
   "is_class": false,
   "is_explicit": false,
   "module": "torch",
   "module_short": "torch",
   "name": "Tensor"
  }
 ],
 "neighbor_indices_new": [
  {
   "is_class": false,
   "is_explicit": false,
   "module": "torch",
   "module_short": "torch",
   "name": "Tensor"
  }
 ],
 "neighbor_shifts": [
  {
   "is_class": false,
   "is_explicit": false,
   "module": "torch",
   "module_short": "torch",
   "name": "Tensor"
  }
 ],
 "neighbor_shifts.type": [
  {
   "is_class": false,
   "is_explicit": false,
   "module": "builtins",
   "module_short": "builtins",
   "name": "builtin_function_or_method"
  }
 ],
 "nl": [
  {
   "is_class": false,
   "is_explicit": false,
   "module": "vesin.torch._neighbors",
   "module_short": "vesin.torch",
   "name": "NeighborList"
  },
  {
   "is_class": false,
   "is_explicit": false,
   "module": "vesin.torch",
   "module_short": "vesin.torch",
   "name": "NeighborList"
  },
  {
   "is_class": false,
   "is_explicit": false,
   "module": "vesin",
   "module_short": "vesin",
   "name": "NeighborList"
  }
 ],
 "nl.compute": [
  {
   "is_class": false,
   "is_explicit": false,
   "module": "vesin.torch._neighbors",
   "module_short": "vesin.torch",
   "name": "NeighborList.compute"
  },
  {
   "is_class": false,
   "is_explicit": false,
   "module": "vesin.torch",
   "module_short": "vesin.torch",
   "name": "NeighborList.compute"
  },
  {
   "is_class": false,
   "is_explicit": false,
   "module": "vesin",
   "module_short": "vesin",
   "name": "NeighborList.compute"
  }
 ],
 "np.array": [
  {
   "is_class": false,
   "is_explicit": false,
   "module": "builtins",
   "module_short": "builtins",
   "name": "builtin_function_or_method"
  },
  {
   "is_class": false,
   "is_explicit": false,
   "module": "numpy",
   "module_short": "numpy",
   "name": "array"
  }
 ],
 "np.eye": [
  {
   "is_class": false,
   "is_explicit": false,
   "module": "builtins",
   "module_short": "builtins",
   "name": "function"
  },
  {
   "is_class": false,
   "is_explicit": false,
   "module": "numpy",
   "module_short": "numpy",
   "name": "eye"
  }
 ],
 "np.random.default_rng": [
  {
   "is_class": false,
   "is_explicit": false,
   "module": "_cython_3_0_11",
   "module_short": "_cython_3_0_11",
   "name": "cython_function_or_method"
  },
  {
   "is_class": false,
   "is_explicit": false,
   "module": "numpy.random",
   "module_short": "numpy.random",
   "name": "default_rng"
  }
 ],
 "np.tile": [
  {
   "is_class": false,
   "is_explicit": false,
   "module": "numpy",
   "module_short": "numpy",
   "name": "_ArrayFunctionDispatcher"
  },
  {
   "is_class": false,
   "is_explicit": false,
   "module": "numpy",
   "module_short": "numpy",
   "name": "tile"
  }
 ],
 "plt.legend": [
  {
   "is_class": false,
   "is_explicit": false,
   "module": "builtins",
   "module_short": "builtins",
   "name": "function"
  },
  {
   "is_class": false,
   "is_explicit": false,
   "module": "matplotlib.pyplot",
   "module_short": "matplotlib.pyplot",
   "name": "legend"
  }
 ],
 "plt.plot": [
  {
   "is_class": false,
   "is_explicit": false,
   "module": "builtins",
   "module_short": "builtins",
   "name": "function"
  },
  {
   "is_class": false,
   "is_explicit": false,
   "module": "matplotlib.pyplot",
   "module_short": "matplotlib.pyplot",
   "name": "plot"
  }
 ],
 "plt.show": [
  {
   "is_class": false,
   "is_explicit": false,
   "module": "builtins",
   "module_short": "builtins",
   "name": "function"
  },
  {
   "is_class": false,
   "is_explicit": false,
   "module": "matplotlib.pyplot",
   "module_short": "matplotlib.pyplot",
   "name": "show"
  }
 ],
 "plt.xlabel": [
  {
   "is_class": false,
   "is_explicit": false,
   "module": "builtins",
   "module_short": "builtins",
   "name": "function"
  },
  {
   "is_class": false,
   "is_explicit": false,
   "module": "matplotlib.pyplot",
   "module_short": "matplotlib.pyplot",
   "name": "xlabel"
  }
 ],
 "plt.ylabel": [
  {
   "is_class": false,
   "is_explicit": false,
   "module": "builtins",
   "module_short": "builtins",
   "name": "function"
  },
  {
   "is_class": false,
   "is_explicit": false,
   "module": "matplotlib.pyplot",
   "module_short": "matplotlib.pyplot",
   "name": "ylabel"
  }
 ],
 "pme": [
  {
   "is_class": false,
   "is_explicit": false,
   "module": "torchpme.calculators.pme",
   "module_short": "torchpme",
   "name": "PMECalculator"
  },
  {
   "is_class": false,
   "is_explicit": false,
   "module": "torchpme.calculators",
   "module_short": "torchpme",
   "name": "PMECalculator"
  },
  {
   "is_class": false,
   "is_explicit": false,
   "module": "torchpme",
   "module_short": "torchpme",
   "name": "PMECalculator"
  }
 ],
 "pme_params": [
  {
   "is_class": false,
   "is_explicit": false,
   "module": "builtins",
   "module_short": "builtins",
   "name": "dict"
  }
 ],
 "positions": [
  {
   "is_class": false,
   "is_explicit": false,
   "module": "torch",
   "module_short": "torch",
   "name": "Tensor"
  }
 ],
 "positions.detach": [
  {
   "is_class": false,
   "is_explicit": false,
   "module": "builtins",
   "module_short": "builtins",
   "name": "builtin_function_or_method"
  }
 ],
 "positions.requires_grad": [
  {
   "is_class": false,
   "is_explicit": false,
   "module": "builtins",
   "module_short": "builtins",
   "name": "bool"
  }
 ],
 "positions_new": [
  {
   "is_class": false,
   "is_explicit": false,
   "module": "torch",
   "module_short": "torch",
   "name": "Tensor"
  }
 ],
 "positions_new.requires_grad": [
  {
   "is_class": false,
   "is_explicit": false,
   "module": "builtins",
   "module_short": "builtins",
   "name": "bool"
  }
 ],
 "potential": [
  {
   "is_class": false,
   "is_explicit": false,
   "module": "torch",
   "module_short": "torch",
   "name": "Tensor"
  }
 ],
 "potential_new": [
  {
   "is_class": false,
   "is_explicit": false,
   "module": "torch",
   "module_short": "torch",
   "name": "Tensor"
  }
 ],
 "rng": [
  {
   "is_class": false,
   "is_explicit": false,
   "module": "numpy.random._generator",
   "module_short": "numpy.random",
   "name": "Generator"
  },
  {
   "is_class": false,
   "is_explicit": false,
   "module": "numpy.random",
   "module_short": "numpy.random",
   "name": "Generator"
  },
  {
   "is_class": false,
   "is_explicit": false,
   "module": "numpy",
   "module_short": "numpy",
   "name": "Generator"
  }
 ],
 "rng.normal": [
  {
   "is_class": false,
   "is_explicit": false,
   "module": "numpy.random._generator",
   "module_short": "numpy.random",
   "name": "Generator.normal"
  },
  {
   "is_class": false,
   "is_explicit": false,
   "module": "numpy.random",
   "module_short": "numpy.random",
   "name": "Generator.normal"
  },
  {
   "is_class": false,
   "is_explicit": false,
   "module": "numpy",
   "module_short": "numpy",
   "name": "Generator.normal"
  }
 ],
 "smearing": [
  {
   "is_class": false,
   "is_explicit": false,
   "module": "builtins",
   "module_short": "builtins",
   "name": "float"
  }
 ],
 "sum_squared_charges": [
  {
   "is_class": false,
   "is_explicit": false,
   "module": "builtins",
   "module_short": "builtins",
   "name": "float"
  }
 ],
 "torch.Tensor": [
  {
   "is_class": true,
   "is_explicit": false,
   "module": "torch",
   "module_short": "torch",
   "name": "Tensor"
  },
  {
   "is_class": true,
   "is_explicit": false,
   "module": "torch._C",
   "module_short": "torch._C",
   "name": "TensorBase"
  },
  {
   "is_class": true,
   "is_explicit": false,
   "module": "torch",
   "module_short": "torch",
   "name": "TensorBase"
  },
  {
   "is_class": false,
   "is_explicit": false,
   "module": "torch",
   "module_short": "torch",
   "name": "Tensor"
  }
 ],
 "torch.Tensor.requires_grad": [
  {
   "is_class": false,
   "is_explicit": true,
   "module": "torch.Tensor",
   "module_short": "torch.Tensor",
   "name": "requires_grad"
  }
 ],
 "torch.autograd.grad": [
  {
   "is_class": false,
   "is_explicit": false,
   "module": "builtins",
   "module_short": "builtins",
   "name": "function"
  },
  {
   "is_class": false,
   "is_explicit": false,
   "module": "torch.autograd",
   "module_short": "torch.autograd",
   "name": "grad"
  }
 ],
 "torch.from_numpy": [
  {
   "is_class": false,
   "is_explicit": false,
   "module": "builtins",
   "module_short": "builtins",
   "name": "builtin_function_or_method"
  },
  {
   "is_class": false,
   "is_explicit": false,
   "module": "torch",
   "module_short": "torch",
   "name": "from_numpy"
  }
 ],
 "torch.linalg.norm": [
  {
   "is_class": false,
   "is_explicit": false,
   "module": "builtins",
   "module_short": "builtins",
   "name": "builtin_function_or_method"
  },
  {
   "is_class": false,
   "is_explicit": false,
   "module": "torch.linalg",
   "module_short": "torch.linalg",
   "name": "norm"
  }
 ],
 "torch.stack": [
  {
   "is_class": false,
   "is_explicit": false,
   "module": "builtins",
   "module_short": "builtins",
   "name": "builtin_function_or_method"
  },
  {
   "is_class": false,
   "is_explicit": false,
   "module": "torch",
   "module_short": "torch",
   "name": "stack"
  }
 ],
 "torch.sum": [
  {
   "is_class": false,
   "is_explicit": false,
   "module": "builtins",
   "module_short": "builtins",
   "name": "builtin_function_or_method"
  },
  {
   "is_class": false,
   "is_explicit": false,
   "module": "torch",
   "module_short": "torch",
   "name": "sum"
  }
 ],
 "torch.tensor": [
  {
   "is_class": false,
   "is_explicit": false,
   "module": "builtins",
   "module_short": "builtins",
   "name": "builtin_function_or_method"
  },
  {
   "is_class": false,
   "is_explicit": false,
   "module": "torch",
   "module_short": "torch",
   "name": "tensor"
  }
 ],
 "torchpme.CoulombPotential": [
  {
   "is_class": true,
   "is_explicit": false,
   "module": "torchpme.potentials.coulomb",
   "module_short": "torchpme",
   "name": "CoulombPotential"
  },
  {
   "is_class": true,
   "is_explicit": false,
   "module": "torchpme.potentials",
   "module_short": "torchpme",
   "name": "CoulombPotential"
  },
  {
   "is_class": true,
   "is_explicit": false,
   "module": "torchpme",
   "module_short": "torchpme",
   "name": "CoulombPotential"
  },
  {
   "is_class": true,
   "is_explicit": false,
   "module": "torchpme.potentials.potential",
   "module_short": "torchpme",
   "name": "Potential"
  },
  {
   "is_class": true,
   "is_explicit": false,
   "module": "torchpme.potentials",
   "module_short": "torchpme",
   "name": "Potential"
  },
  {
   "is_class": true,
   "is_explicit": false,
   "module": "torchpme",
   "module_short": "torchpme",
   "name": "Potential"
  },
  {
   "is_class": true,
   "is_explicit": false,
   "module": "torch.nn.modules.module",
   "module_short": "torch.nn",
   "name": "Module"
  },
  {
   "is_class": true,
   "is_explicit": false,
   "module": "torch.nn.modules",
   "module_short": "torch.nn",
   "name": "Module"
  },
  {
   "is_class": true,
   "is_explicit": false,
   "module": "torch.nn",
   "module_short": "torch.nn",
   "name": "Module"
  },
  {
   "is_class": true,
   "is_explicit": false,
   "module": "torch",
   "module_short": "torch",
   "name": "Module"
  },
  {
   "is_class": false,
   "is_explicit": false,
   "module": "torchpme",
   "module_short": "torchpme",
   "name": "CoulombPotential"
  }
 ],
 "torchpme.PMECalculator": [
  {
   "is_class": true,
   "is_explicit": false,
   "module": "torchpme.calculators.pme",
   "module_short": "torchpme",
   "name": "PMECalculator"
  },
  {
   "is_class": true,
   "is_explicit": false,
   "module": "torchpme.calculators",
   "module_short": "torchpme",
   "name": "PMECalculator"
  },
  {
   "is_class": true,
   "is_explicit": false,
   "module": "torchpme",
   "module_short": "torchpme",
   "name": "PMECalculator"
  },
  {
   "is_class": true,
   "is_explicit": false,
   "module": "torchpme.calculators.calculator",
   "module_short": "torchpme",
   "name": "Calculator"
  },
  {
   "is_class": true,
   "is_explicit": false,
   "module": "torchpme.calculators",
   "module_short": "torchpme",
   "name": "Calculator"
  },
  {
   "is_class": true,
   "is_explicit": false,
   "module": "torchpme",
   "module_short": "torchpme",
   "name": "Calculator"
  },
  {
   "is_class": true,
   "is_explicit": false,
   "module": "torch.nn.modules.module",
   "module_short": "torch.nn",
   "name": "Module"
  },
  {
   "is_class": true,
   "is_explicit": false,
   "module": "torch.nn.modules",
   "module_short": "torch.nn",
   "name": "Module"
  },
  {
   "is_class": true,
   "is_explicit": false,
   "module": "torch.nn",
   "module_short": "torch.nn",
   "name": "Module"
  },
  {
   "is_class": true,
   "is_explicit": false,
   "module": "torch",
   "module_short": "torch",
   "name": "Module"
  },
  {
   "is_class": false,
   "is_explicit": false,
   "module": "torchpme",
   "module_short": "torchpme",
   "name": "PMECalculator"
  }
 ],
 "torchpme.utils.tune_pme": [
  {
   "is_class": false,
   "is_explicit": false,
   "module": "builtins",
   "module_short": "builtins",
   "name": "function"
  },
  {
   "is_class": false,
   "is_explicit": false,
   "module": "torchpme.utils",
   "module_short": "torchpme.utils",
   "name": "tune_pme"
  }
 ],
 "vesin.NeighborList": [
  {
   "is_class": true,
   "is_explicit": false,
   "module": "vesin._neighbors",
   "module_short": "vesin",
   "name": "NeighborList"
  },
  {
   "is_class": true,
   "is_explicit": false,
   "module": "vesin",
   "module_short": "vesin",
   "name": "NeighborList"
  },
  {
   "is_class": false,
   "is_explicit": false,
   "module": "vesin",
   "module_short": "vesin",
   "name": "NeighborList"
  }
 ],
 "vesin.torch.NeighborList": [
  {
   "is_class": true,
   "is_explicit": false,
   "module": "vesin.torch._neighbors",
   "module_short": "vesin.torch",
   "name": "NeighborList"
  },
  {
   "is_class": true,
   "is_explicit": false,
   "module": "vesin.torch",
   "module_short": "vesin.torch",
   "name": "NeighborList"
  },
  {
   "is_class": true,
   "is_explicit": false,
   "module": "vesin",
   "module_short": "vesin",
   "name": "NeighborList"
  },
  {
   "is_class": false,
   "is_explicit": false,
   "module": "vesin.torch",
   "module_short": "vesin.torch",
   "name": "NeighborList"
  },
  {
   "is_class": false,
   "is_explicit": false,
   "module": "vesin.torch",
   "module_short": "vesin.torch",
   "name": "NeighborList"
  }
 ]
}